model_archiver/__init__.py
model_archiver/arg_parser.py
model_archiver/model_archiver_error.py
model_archiver/model_packaging.py
model_archiver/model_packaging_utils.py
model_archiver/version.py
model_archiver/version.txt
model_archiver/manifest_components/__init__.py
model_archiver/manifest_components/manifest.py
model_archiver/manifest_components/model.py
torch_model_archiver_ag-0.6.0b20220624.dist-info/LICENSE
torch_model_archiver_ag-0.6.0b20220624.dist-info/METADATA
torch_model_archiver_ag-0.6.0b20220624.dist-info/WHEEL
torch_model_archiver_ag-0.6.0b20220624.dist-info/entry_points.txt
torch_model_archiver_ag-0.6.0b20220624.dist-info/top_level.txt
torch_model_archiver_ag-0.6.0b20220624.dist-info/RECORD
