Metadata-Version: 2.1
Name: torch-model-archiver-ag
Version: 0.6.0b20220624
Summary: Torch Model Archiver is used for creating archives of trained neural net models that can be consumed by TorchServe inference
Home-page: https://github.com/pytorch/serve/model-archiver/
Author: PyTorch Serving team
Author-email: noreply@noreply.com
License: Apache License Version 2.0
Keywords: TorchServe Torch Model Archive Archiver Server Serving Deep Learning Inference AI
License-File: LICENSE
Requires-Dist: future
Requires-Dist: enum-compat
